src/__init__.py
src/blog/__init__.py
src/blog/blog.py
src/blog/layout.py
src/builder/builder.py
src/cli.py
src/config.py
src/converters/__init__.py
src/converters/handlebars.py
src/converters/markdown.py
src/dataclasses/asset_data.py
src/dataclasses/config_data.py
src/dataclasses/content_data.py
src/entities/image.py
src/entities/inline_image.py
src/entities/markdown_image.py
src/entities/obsidian_embed.py
src/entities/obsidian_link.py
src/entities/parser.py
src/entities/reference_image.py
src/lib/fs.py
src/lib/http_server.py
src/lib/watcher.py
src/obsidian/__init__.py
src/obsidian/page.py
src/obsidian/vault.py
src/preprocessors/further_reading.py
src/preprocessors/include_header.py
src/preprocessors/note_delimeters.py
src/tasks/__init__.py
src/tasks/builder.py
src/tasks/preflight_check.py
src/tasks/server.py
src/tasks/watcher.py
src/tree/node.py
obsidian_blog-0.2.2.dist-info/entry_points.txt
obsidian_blog-0.2.2.dist-info/WHEEL
obsidian_blog-0.2.2.dist-info/METADATA
obsidian_blog-0.2.2.dist-info/RECORD
